pkgbuilder/__init__.py
pkgbuilder/__main__.py
pkgbuilder/aur.py
pkgbuilder/build.py
pkgbuilder/exceptions.py
pkgbuilder/package.py
pkgbuilder/pbds.py
pkgbuilder/transaction.py
pkgbuilder/ui.py
pkgbuilder/upgrade.py
pkgbuilder/utils.py
pkgbuilder/wrapper.py
pkgbuilder/data/pkgbuilder.ini.skel
pkgbuilder-4.3.2.data/data/share/locale/ar/LC_MESSAGES/pkgbuilder.mo
pkgbuilder-4.3.2.data/data/share/locale/cs/LC_MESSAGES/pkgbuilder.mo
pkgbuilder-4.3.2.data/data/share/locale/de/LC_MESSAGES/pkgbuilder.mo
pkgbuilder-4.3.2.data/data/share/locale/es/LC_MESSAGES/pkgbuilder.mo
pkgbuilder-4.3.2.data/data/share/locale/id/LC_MESSAGES/pkgbuilder.mo
pkgbuilder-4.3.2.data/data/share/locale/it/LC_MESSAGES/pkgbuilder.mo
pkgbuilder-4.3.2.data/data/share/locale/ja/LC_MESSAGES/pkgbuilder.mo
pkgbuilder-4.3.2.data/data/share/locale/pl/LC_MESSAGES/pkgbuilder.mo
pkgbuilder-4.3.2.data/data/share/locale/pt/LC_MESSAGES/pkgbuilder.mo
pkgbuilder-4.3.2.data/data/share/locale/sk/LC_MESSAGES/pkgbuilder.mo
pkgbuilder-4.3.2.data/data/share/locale/sv/LC_MESSAGES/pkgbuilder.mo
pkgbuilder-4.3.2.data/data/share/locale/tr/LC_MESSAGES/pkgbuilder.mo
pkgbuilder-4.3.2.data/data/share/locale/vi/LC_MESSAGES/pkgbuilder.mo
pkgbuilder-4.3.2.data/data/share/locale/zh_CN/LC_MESSAGES/pkgbuilder.mo
pkgbuilder-4.3.2.data/data/share/man/man8/pb.8.gz
pkgbuilder-4.3.2.data/data/share/man/man8/pkgbuilder.8.gz
pkgbuilder-4.3.2.dist-info/AUTHORS
pkgbuilder-4.3.2.dist-info/LICENSE
pkgbuilder-4.3.2.dist-info/METADATA
pkgbuilder-4.3.2.dist-info/WHEEL
pkgbuilder-4.3.2.dist-info/entry_points.txt
pkgbuilder-4.3.2.dist-info/top_level.txt
pkgbuilder-4.3.2.dist-info/RECORD
