Metadata-Version: 2.1
Name: pkgbuilder
Version: 4.3.2
Summary: An AUR helper (and library) in Python 3.
Home-page: https://github.com/Kwpolska/pkgbuilder
Author: Chris Warrick
Author-email: chris@chriswarrick.com
License: 3-clause BSD
Keywords: arch pkgbuild
Platform: Arch Linux
Classifier: Development Status :: 6 - Mature
Classifier: Environment :: Console
Classifier: Intended Audience :: End Users/Desktop
Classifier: Intended Audience :: System Administrators
Classifier: License :: OSI Approved :: BSD License
Classifier: Natural Language :: English
Classifier: Operating System :: POSIX :: Linux
Classifier: Programming Language :: Python
Classifier: Programming Language :: Python :: 3
Classifier: Programming Language :: Python :: 3.7
Classifier: Topic :: System
Classifier: Topic :: System :: Archiving :: Packaging
Classifier: Topic :: Utilities
License-File: LICENSE
License-File: AUTHORS
Requires-Dist: pyalpm
Requires-Dist: requests
Requires-Dist: srcinfo
